django_health_check_prometheus/__init__.py
django_health_check_prometheus/apps.py
django_health_check_prometheus/backends.py
django_health_check_prometheus/collector.py
django_health_check_prometheus-0.1.0.dist-info/LICENSE
django_health_check_prometheus-0.1.0.dist-info/WHEEL
django_health_check_prometheus-0.1.0.dist-info/METADATA
django_health_check_prometheus-0.1.0.dist-info/RECORD
