Metadata-Version: 2.1
Name: django-health-check-prometheus
Version: 0.1.0
Summary: This is a prometheus adapter for django health check
Author: MrLYC
Author-email: fimyikong@gmai.com
Requires-Python: >=3.6
Classifier: Programming Language :: Python :: 3
Classifier: Programming Language :: Python :: 3.10
Classifier: Programming Language :: Python :: 3.6
Classifier: Programming Language :: Python :: 3.7
Classifier: Programming Language :: Python :: 3.8
Classifier: Programming Language :: Python :: 3.9
Requires-Dist: django-health-check (>=3.16.0)
